pygosql/__init__.py
pygosql/pygosql.py
pygosql/pygosql.pyi
pygosql/gosql/go.mod
pygosql/gosql/go.sum
pygosql/gosql/go_launcher.ps1
pygosql/gosql/main.go
pygosql/gosql/stub.go
pygosql/gosql/database/database.go
pygosql/gosql/database/sql_io.go
pygosql/gosql/server/server.go
pygosql/gosql/server/sql_to_http.go
pygosql/gosql/setup/config.go
pygosql/gosql/setup/map.go
pygosql-0.3.0.dist-info/licenses/LICENSE
pygosql-0.3.0.dist-info/METADATA
pygosql-0.3.0.dist-info/WHEEL
pygosql-0.3.0.dist-info/top_level.txt
pygosql-0.3.0.dist-info/RECORD
