Metadata-Version: 2.4
Name: pygosql
Version: 0.3.0
Summary: Python wrapper for HTTPS requesting SQL via Go
Author: genderlesspit
License: MIT
Project-URL: Homepage, https://github.com/genderlesspit/pygosql
Requires-Python: >=3.8
License-File: LICENSE
Requires-Dist: loguru>=0.5.3
Requires-Dist: toomanyports>=0.1
Requires-Dist: aiohttp>=3.8.1
Requires-Dist: pygops
Dynamic: license-file
